copypasta_search/__init__.py
copypasta_search-1.3.dist-info/LICENSE
copypasta_search-1.3.dist-info/METADATA
copypasta_search-1.3.dist-info/WHEEL
copypasta_search-1.3.dist-info/entry_points.txt
copypasta_search-1.3.dist-info/top_level.txt
copypasta_search-1.3.dist-info/RECORD
