Metadata-Version: 2.1
Name: copypasta-search
Version: 1.3
Summary: Python Copypasta Search using Reddit
Home-page: https://github.com/lolei/copypasta-search
Author: Lorenz Leitner
Author-email: lrnz.ltnr@gmail.com
License: UNKNOWN
Platform: UNKNOWN
Classifier: Programming Language :: Python :: 3.8
Classifier: License :: OSI Approved :: MIT License
Classifier: Operating System :: OS Independent
Requires-Python: >=3.5
License-File: LICENSE
Requires-Dist: praw (==7.3.0)
Requires-Dist: pyperclip (==1.8.2)
